README.md
setup.py
packtivity_kube_plugin.egg-info/PKG-INFO
packtivity_kube_plugin.egg-info/SOURCES.txt
packtivity_kube_plugin.egg-info/dependency_links.txt
packtivity_kube_plugin.egg-info/requires.txt
packtivity_kube_plugin.egg-info/top_level.txt
packtivitykube/__init__.py
packtivitykube/state_hostpath.py
packtivitykube/state_sharedvol.py