Metadata-Version: 1.0
Name: packtivity-kube-plugin
Version: 0.0.6
Summary: packtivity kubernetes plugin
Home-page: UNKNOWN
Author: Lukas Heinrich
Author-email: lukas.heinrich@cern.ch
License: UNKNOWN
Platform: UNKNOWN
